pool_sharq/__init__.py
pool_sharq/_fetch/_download_test_data.py
pool_sharq/_fetch/_poolq_downloader.py
pool_sharq/_poolq_python/_poolq_module.py
pool_sharq/_poolq_python/_supporting_functions/_build_poolq_shell_executable.py
pool_sharq/_poolq_python/_supporting_functions/_get_downloaded_poolq_version.py
pool_sharq/_poolq_python/_supporting_functions/_run_poolq.py
pool_sharq-0.0.12.dist-info/LICENSE
pool_sharq-0.0.12.dist-info/METADATA
pool_sharq-0.0.12.dist-info/WHEEL
pool_sharq-0.0.12.dist-info/top_level.txt
pool_sharq-0.0.12.dist-info/RECORD
