Metadata-Version: 2.1
Name: pool-sharq
Version: 0.0.12
Summary: pool-sharq: python interface for Broad Institute GPP's poolq software.
Home-page: https://github.com/mvinyard/pool-sharq
Author: Michael E. Vinyard - Harvard University - Massachussetts General Hospital - Broad Institute of MIT and Harvard
Author-email: mvinyard@broadinstitute.org
License: MIT
Platform: UNKNOWN
Classifier: Development Status :: 2 - Pre-Alpha
Classifier: Programming Language :: Python :: 3.7
Classifier: Intended Audience :: Science/Research
Classifier: Topic :: Scientific/Engineering :: Bio-Informatics
Requires-Python: >3.7.0
License-File: LICENSE
Requires-Dist: beautifulsoup4 (>=4.10.0)
Requires-Dist: licorice (>=0.0.2)
Requires-Dist: pandas (>=1.3.4)
Requires-Dist: pyrequisites (>=0.0.2)
Requires-Dist: requests (>=2.26.0)
Requires-Dist: tqdm (>=4.62.3)
